
[
  {
    "id": 0,
    "rarity": 0,
    "collab": 0,
    "forms": [
      { "stage": 1, "name": "ネコ", "description": "安価で生産できる基本キャラ" },
      { "stage": 2, "name": "ネコビルダー", "description": "鍛えぬいた筋肉がチャームポイントの\n基本キャラ" },
      { "stage": 3, "name": "ネコモヒカン", "description": "鍛えぬいた筋肉に男前なタテガミが\nチャームポイントの基本キャラ" }
    ]
  },
  {
    "id": 1,
    "rarity": 0,
    "collab": 0,
    "forms": [
      { "stage": 1, "name": "タンクネコ", "description": "体力を多く備えた盾用のキャラ\n攻撃力はスズメの涙ほど(範囲攻撃)" },
      { "stage": 2, "name": "ネコカベ", "description": "まさにカベに徹する為の盾専用キャラ\n攻撃力はあいかわらず(範囲攻撃)" },
      { "stage": 3, "name": "ゴムネコ", "description": "まさにカベに徹する為の盾専用キャラ\nゴムの弾力を利用してさらに強化されたが\n攻撃力はあいかわらず(範囲攻撃)" }
    ]
  },
  {
    "id": 2,
    "rarity": 0,
    "collab": 0,
    "forms": [
      { "stage": 1, "name": "バトルネコ", "description": "戦闘向きのキャラ\n｢赤い敵｣にめっぽう強い" },
      { "stage": 2, "name": "勇者ネコ", "description": "勇者にあこがれる戦闘向きのキャラ\n｢赤い敵｣にめっぽう強い" },
      { "stage": 3, "name": "暗黒ネコ", "description": "ダークヒーローにも憧れた\n戦闘向きのキャラ\n｢赤い敵｣にめっぽう強い" }
    ]
  },
  {
    "id": 3,
    "rarity": 0,
    "collab": 0,
    "forms": [
      { "stage": 1, "name": "キモネコ", "description": "遠くの敵を攻撃できる遠距離型キャラ\n単発だけなら攻撃力はハイクラス" },
      { "stage": 2, "name": "美脚ネコ", "description": "美しすぎる足が自慢の遠距離型キャラ\n単発だけなら攻撃力はハイクラス" },
      { "stage": 3, "name": "ムキあしネコ", "description": "筋肉美が自慢の遠距離型キャラ\n単発だけなら攻撃力はハイクラス\n｢エイリアン｣にめっぽう強い" }
    ]
  },
  {
    "id": 4,
    "rarity": 0,
    "collab": 0,
    "forms": [
      { "stage": 1, "name": "ウシネコ", "description": "俊敏な動きで移動力に優れたキャラ\n攻撃回数もハンパない" },
      { "stage": 2, "name": "ネコキリン", "description": "俊敏な動きで移動力に優れたキャラ\n長い首でのヘッドバンギングが笑える" },
      { "stage": 3, "name": "ネコライオン", "description": "俊敏な動きで移動力に優れたキャラ\n頭のタテガミは拭き掃除にも使える" }
    ]
  },
  {
    "id": 5,
    "rarity": 0,
    "collab": 0,
    "forms": [
      { "stage": 1, "name": "ネコノトリ", "description": "体力は少ないが敵をまとめて一掃する\n超破壊力を持ったキャラ(範囲攻撃)" },
      { "stage": 2, "name": "ネコＵＦＯ", "description": "重力を超越した改造にゃんこ\n敵をまとめてお仕置き可能(範囲攻撃)" },
      { "stage": 3, "name": "天空のネコ", "description": "放たれる光弾は巨大都市を一瞬で焼き払った\nと言われる空中都市型にゃんこ\nごくたまに｢天使｣の攻撃力を下げる(範囲攻撃)" }
    ]
  },
  {
    "id": 6,
    "rarity": 0,
    "collab": 0,
    "forms": [
      { "stage": 1, "name": "ネコフィッシュ", "description": "戦闘向きの高級キャラ\n｢赤い敵｣にはめっぽう強い" },
      { "stage": 2, "name": "ネコクジラ", "description": "肉食クジラに進化した高級戦闘キャラ\n｢赤い敵｣にはめっぽう強い" },
      { "stage": 3, "name": "ネコ島", "description": "にゃんこ達のバカンスに最適な形状にまで\n進化したキャラ。｢赤い敵｣にはめっぽう強く\nごくたまにクリティカル攻撃を放つ" }
    ]
  },
  {
    "id": 7,
    "rarity": 0,
    "collab": 0,
    "forms": [
      { "stage": 1, "name": "ネコトカゲ", "description": "遠くの敵を攻撃できる遠距離型キャラ\n単発だけなら攻撃力はピカイチ" },
      { "stage": 2, "name": "ネコドラゴン", "description": "幻想世界から降臨した遠距離型キャラ\n単発だけなら攻撃力はピカイチ" },
      { "stage": 3, "name": "ネコキングドラゴン", "description": "ドラゴン界のエリートまで上り詰めた\n遠距離型キャラ\n単発だけなら攻撃力はピカイチ" }
    ]
  },
  {
    "id": 8,
    "rarity": 0,
    "collab": 0,
    "forms": [
      { "stage": 1, "name": "巨神ネコ", "description": "超絶破壊力＆強靭な体力を備えた\n最高級のキャラ(範囲攻撃)" },
      { "stage": 2, "name": "ネコダラボッチ", "description": "超絶破壊力＆強靭な体力を備えた\n破壊をつかさどるネコ神様(範囲攻撃)" },
      { "stage": 3, "name": "ネコジャラミ", "description": "ごくたまに敵をふっとばす\n破壊をつかさどる巨大ネコ(範囲攻撃)\nＴシャツが伸びるので良い子はマネしない方がいい" }
    ]
  },
  {
    "id": 643,
    "rarity": 0,
    "collab": 0,
    "forms": [
      { "stage": 1, "name": "ネコ超人", "description": "運命を覆すために現れたヒトを超越したネコ\n素早く敵に近づき、長い尻尾で攻撃する\n古代種に超ダメージを与える(全方位攻撃)" },
      { "stage": 2, "name": "ネコ超人Ⅱ", "description": "自らの意志に従い戦いに突き進むネコ\nマッスルパワーで自由を追い求める\n古代種に超ダメージを与える(全方位攻撃)" },
      { "stage": 3, "name": "真ネコ超人", "description": "遺伝子に刻まれた「人類ネコ化計画」の遂行\n永遠回帰の末、永きに渡る歳月を経て今動き出す\n古代種に超ダメージを与える(全方位攻撃)" }
    ]
  }
]
